buffalo/__init__.py
buffalo/algo/__init__.py
buffalo/algo/_als.cpython-39-x86_64-linux-gnu.so
buffalo/algo/_bpr.cpython-39-x86_64-linux-gnu.so
buffalo/algo/_cfr.cpython-39-x86_64-linux-gnu.so
buffalo/algo/_eals.cpython-39-x86_64-linux-gnu.so
buffalo/algo/_plsi.cpython-39-x86_64-linux-gnu.so
buffalo/algo/_w2v.cpython-39-x86_64-linux-gnu.so
buffalo/algo/_warp.cpython-39-x86_64-linux-gnu.so
buffalo/algo/als.py
buffalo/algo/base.py
buffalo/algo/bpr.py
buffalo/algo/cfr.py
buffalo/algo/eals.py
buffalo/algo/options.py
buffalo/algo/plsi.py
buffalo/algo/w2v.py
buffalo/algo/warp.py
buffalo/data/__init__.py
buffalo/data/base.py
buffalo/data/buffered_data.py
buffalo/data/fileio.cpython-39-x86_64-linux-gnu.so
buffalo/data/mm.py
buffalo/data/prepro.py
buffalo/data/stream.py
buffalo/evaluate/__init__.py
buffalo/evaluate/base.py
buffalo/misc/__init__.py
buffalo/misc/_aux.py
buffalo/misc/_log.cpython-39-x86_64-linux-gnu.so
buffalo/misc/log.py
buffalo/misc/util.py
buffalo/parallel/__init__.py
buffalo/parallel/_core.cpython-39-x86_64-linux-gnu.so
buffalo/parallel/base.py
buffalo_test-2.0.5.dist-info/LICENSE
buffalo_test-2.0.5.dist-info/METADATA
buffalo_test-2.0.5.dist-info/NOTICE.md
buffalo_test-2.0.5.dist-info/WHEEL
buffalo_test-2.0.5.dist-info/top_level.txt
buffalo_test-2.0.5.dist-info/RECORD
